xml_generator/__init__.py
xml_generator/types.py
xml_generator_seobaeksol-0.5.0.dist-info/LICENSE
xml_generator_seobaeksol-0.5.0.dist-info/METADATA
xml_generator_seobaeksol-0.5.0.dist-info/WHEEL
xml_generator_seobaeksol-0.5.0.dist-info/top_level.txt
xml_generator_seobaeksol-0.5.0.dist-info/RECORD
