Metadata-Version: 2.1
Name: xml-generator-seobaeksol
Version: 0.5.0
Summary: Comprehensive XML generator for Python
Home-page: https://github.com/seobaeksol/xml-generator
Author: seobaeksol
Author-email: suyoung154@example.com
Classifier: Programming Language :: Python :: 3
Classifier: License :: OSI Approved :: MIT License
Classifier: Operating System :: OS Independent
Requires-Python: >=3.6
License-File: LICENSE
